cubicweb_rqlcontroller/__init__.py
cubicweb_rqlcontroller/__pkginfo__.py
cubicweb_rqlcontroller/predicates.py
cubicweb_rqlcontroller/rql_schema_holder.py
cubicweb_rqlcontroller/views.py
cubicweb_rqlcontroller/i18n/en.po
cubicweb_rqlcontroller/i18n/es.po
cubicweb_rqlcontroller/i18n/fr.po
cubicweb_rqlcontroller-1.1.0.dist-info/METADATA
cubicweb_rqlcontroller-1.1.0.dist-info/WHEEL
cubicweb_rqlcontroller-1.1.0.dist-info/entry_points.txt
cubicweb_rqlcontroller-1.1.0.dist-info/top_level.txt
cubicweb_rqlcontroller-1.1.0.dist-info/RECORD
