Metadata-Version: 2.4
Name: cubicweb-rqlcontroller
Version: 1.1.0
Summary: restfull RQL edition capabilities for CubicWeb
Home-page: https://forge.extranet.logilab.fr/cubicweb/cubes/cubicweb-rqlcontroller
Author: LOGILAB S.A. (Paris, FRANCE)
Author-email: contact@logilab.fr
License: LGPL
Classifier: Environment :: Web Environment
Classifier: Framework :: CubicWeb
Classifier: Programming Language :: Python
Classifier: Programming Language :: Python :: 3
Classifier: Programming Language :: Python :: 3 :: Only
Classifier: Programming Language :: JavaScript
Requires-Python: >=3.9.2
Requires-Dist: cubicweb<6.0.0,>=4.5.3
Requires-Dist: cubicweb-web<2.0.0,>=1.6.1
Dynamic: author
Dynamic: author-email
Dynamic: classifier
Dynamic: description
Dynamic: home-page
Dynamic: license
Dynamic: requires-dist
Dynamic: requires-python
Dynamic: summary
